<?xml version="1.0" encoding="UTF-8"?><record_update table="catalog_ui_policy_action">
    <catalog_ui_policy_action action="INSERT_OR_UPDATE">
        <catalog_item display_value="Submit Expenses">2a5d814847000210b0eaf19f016d434e</catalog_item>
        <catalog_variable>IO:65bf17a747640210b0eaf19f016d438c</catalog_variable>
        <cleared>false</cleared>
        <disabled>ignore</disabled>
        <field/>
        <mandatory>ignore</mandatory>
        <order>100</order>
        <sys_class_name>catalog_ui_policy_action</sys_class_name>
        <sys_created_by>admin</sys_created_by>
        <sys_created_on>2024-03-01 14:50:15</sys_created_on>
        <sys_id>cf9727ef47640210b0eaf19f016d4310</sys_id>
        <sys_mod_count>0</sys_mod_count>
        <sys_name>expenses_submit</sys_name>
        <sys_package display_value="Reisekosten" source="d17c3ad697bef9107f203d37f053af19">d17c3ad697bef9107f203d37f053af19</sys_package>
        <sys_policy/>
        <sys_scope display_value="Reisekosten">d17c3ad697bef9107f203d37f053af19</sys_scope>
        <sys_update_name>catalog_ui_policy_action_cf9727ef47640210b0eaf19f016d4310</sys_update_name>
        <sys_updated_by>admin</sys_updated_by>
        <sys_updated_on>2024-03-01 14:50:15</sys_updated_on>
        <table/>
        <ui_policy display_value="Reisekostencontainer nur dann anzeigen, wenn Reisekosten (travel expenses) ausgewählt wurde">fbe6a7af47640210b0eaf19f016d43f3</ui_policy>
        <variable>expenses_submit</variable>
        <variable_set/>
        <visible>true</visible>
    </catalog_ui_policy_action>
</record_update>
